Metadata-Version: 2.1
Name: Taxo-Matcher
Version: 0.1
Summary: A tool for parsing and extracting taxon synonyms.
Home-page: https://github.com/Lswhiteh/taxo-matcher
Author: Logan Whitehouse
Author-email: lswhiteh@unc.edu
License: MIT
Project-URL: Issues, https://github.com/Lswhiteh/taxo-matcher/issues
Project-URL: GitHub, https://github.com/Lswhiteh/taxo-matcher
Keywords: population genetics,phylogenetics,taxonomy
Classifier: Programming Language :: Python :: 3
Classifier: Operating System :: OS Independent
Requires-Python: >=3.6
License-File: LICENSE
